sysidentpy/__init__.py
sysidentpy/narmax_base.py
sysidentpy/basis_function/__init__.py
sysidentpy/basis_function/_bernstein.py
sysidentpy/basis_function/_bilinear.py
sysidentpy/basis_function/_fourier.py
sysidentpy/basis_function/_hermite.py
sysidentpy/basis_function/_hermite_normalized.py
sysidentpy/basis_function/_laguerre.py
sysidentpy/basis_function/_legendre.py
sysidentpy/basis_function/_polynomial.py
sysidentpy/basis_function/basis_function_base.py
sysidentpy/basis_function/tests/__init__.py
sysidentpy/basis_function/tests/test_basis_functions.py
sysidentpy/basis_function/tests/test_bernstein.py
sysidentpy/basis_function/tests/test_bilinear.py
sysidentpy/basis_function/tests/test_hermite.py
sysidentpy/basis_function/tests/test_hermite_normalized.py
sysidentpy/basis_function/tests/test_laguerre.py
sysidentpy/basis_function/tests/test_legendre.py
sysidentpy/general_estimators/__init__.py
sysidentpy/general_estimators/narx.py
sysidentpy/general_estimators/tests/__init__.py
sysidentpy/general_estimators/tests/test_general_narx.py
sysidentpy/metaheuristics/__init__.py
sysidentpy/metaheuristics/bpsogsa.py
sysidentpy/metaheuristics/tests/__init__.py
sysidentpy/metaheuristics/tests/test_bpsogsa.py
sysidentpy/metrics/__init__.py
sysidentpy/metrics/_regression.py
sysidentpy/metrics/tests/__init__.py
sysidentpy/metrics/tests/test_regression.py
sysidentpy/model_structure_selection/__init__.py
sysidentpy/model_structure_selection/accelerated_orthogonal_least_squares.py
sysidentpy/model_structure_selection/entropic_regression.py
sysidentpy/model_structure_selection/forward_regression_orthogonal_least_squares.py
sysidentpy/model_structure_selection/meta_model_structure_selection.py
sysidentpy/model_structure_selection/ofr_base.py
sysidentpy/model_structure_selection/sobolev_orthogonal_forward_regression.py
sysidentpy/model_structure_selection/tests/__init__.py
sysidentpy/model_structure_selection/tests/test_aols.py
sysidentpy/model_structure_selection/tests/test_er.py
sysidentpy-0.6.0.dist-info/licenses/AUTHORS
sysidentpy-0.6.0.dist-info/licenses/LICENSE
sysidentpy-0.6.0.dist-info/METADATA
sysidentpy-0.6.0.dist-info/WHEEL
sysidentpy-0.6.0.dist-info/top_level.txt
sysidentpy-0.6.0.dist-info/RECORD
