Metadata-Version: 2.4
Name: sysidentpy
Version: 0.6.0
Summary: A Python Package For System Identification Using NARMAX Models
Author: Wilson Rocha Lacerda Junior
Author-email: wilsonrljr@outlook.com
Maintainer-email: Wilson Rocha Lacerda Junior <wilsonrljr@outlook.com>
License: BSD 3-Clause License
Project-URL: homepage, http://sysidentpy.org
Project-URL: documentation, http://sysidentpy.org/
Project-URL: repository, https://github.com/wilsonrljr/sysidentpy
Project-URL: changelog, https://github.com/wilsonrljr/sysidentpy/blob/master/CHANGELOG
Keywords: data-science,forecasting,NARMAX,NARX,system-identification,machine-learning,time-series,time-series-analysis,time-series-classification,time-series-regression
Classifier: Intended Audience :: Science/Research
Classifier: Intended Audience :: Information Technology
Classifier: Intended Audience :: Developers
Classifier: Intended Audience :: Education
Classifier: License :: OSI Approved :: BSD License
Classifier: Programming Language :: Python
Classifier: Programming Language :: Python :: 3 :: Only
Classifier: Programming Language :: Python :: 3.8
Classifier: Programming Language :: Python :: 3.9
Classifier: Programming Language :: Python :: 3.10
Classifier: Programming Language :: Python :: 3.11
Classifier: Programming Language :: Python :: 3.12
Classifier: Development Status :: 5 - Production/Stable
Classifier: Intended Audience :: Science/Research
Classifier: Topic :: Scientific/Engineering
Classifier: Topic :: Software Development
Classifier: Topic :: Scientific/Engineering :: Artificial Intelligence
Classifier: Topic :: Software Development :: Libraries :: Application Frameworks
Classifier: Topic :: Software Development :: Libraries :: Python Modules
Classifier: Topic :: Software Development :: Libraries
Classifier: Operating System :: OS Independent
Requires-Python: <3.13,>=3.8
License-File: LICENSE
License-File: AUTHORS
Requires-Dist: numpy<2.0,>=1.19.2
Requires-Dist: scipy>=1.8.0
Requires-Dist: matplotlib>=3.3.2
Provides-Extra: dev
Requires-Dist: pytest<8.0.0,>=7.0.0; extra == "dev"
Requires-Dist: pytest-cov<4.0.0,>=2.12.0; extra == "dev"
Requires-Dist: flake8<7.0.0,>=3.8.3; extra == "dev"
Requires-Dist: black>=23.3.0; extra == "dev"
Requires-Dist: isort<6.0.0,>=5.0.6; extra == "dev"
Requires-Dist: pre-commit; extra == "dev"
Requires-Dist: ruff<3.0.0,>=0.2.2; extra == "dev"
Provides-Extra: examples
Requires-Dist: scikit-learn; extra == "examples"
Requires-Dist: catboost; extra == "examples"
Provides-Extra: docs
Requires-Dist: mkdocs<2.0.0,>=1.1.2; extra == "docs"
Requires-Dist: mkdocs-material<=9.6.6,>=8.1.4; extra == "docs"
Requires-Dist: mdx-include<2.0.0,>=1.4.1; extra == "docs"
Requires-Dist: mkdocs-markdownextradata-plugin<=0.2.6,>=0.1.7; extra == "docs"
Requires-Dist: typer<0.5.0,>=0.4.1; extra == "docs"
Requires-Dist: pyyaml<7.0.0,>=5.3.1; extra == "docs"
Requires-Dist: mkdocstrings[python]<0.29,>=0.25.2; extra == "docs"
Requires-Dist: mkdocs-redirects>=1.2.0; extra == "docs"
Requires-Dist: mkdocs-minify-plugin<=0.8.0; extra == "docs"
Requires-Dist: mkdocs-glightbox<=0.4.0; extra == "docs"
Requires-Dist: mkdocs-jupyter<=0.25.1; extra == "docs"
Requires-Dist: mkdocs-autorefs>=1.3.1; extra == "docs"
Requires-Dist: jinja2>=3.0.3; extra == "docs"
Provides-Extra: all
Requires-Dist: torch<2.4.0,>=1.7.1; extra == "all"
Dynamic: license-file
